LICENSE
README.rst
setup.py
doptools/__init__.py
doptools.egg-info/PKG-INFO
doptools.egg-info/SOURCES.txt
doptools.egg-info/dependency_links.txt
doptools.egg-info/entry_points.txt
doptools.egg-info/requires.txt
doptools.egg-info/top_level.txt
doptools/chem/__init__.py
doptools/chem/chem_features.py
doptools/chem/coloratom.py
doptools/chem/solvents.py
doptools/chem/utils.py
doptools/cli/__init__.py
doptools/cli/ensemble_model_rebuilding.py
doptools/cli/launch_optimizer.py
doptools/cli/launch_preparer.py
doptools/cli/plotter.py
doptools/cli/rebuilder.py
doptools/optimizer/__init__.py
doptools/optimizer/config.py
doptools/optimizer/optimizer.py
doptools/optimizer/preparer.py
doptools/optimizer/utils.py
test/test_chem_features.py