Metadata-Version: 2.1
Name: doptools
Version: 1.3.9
Summary: A package for calculation of molecular descriptors in Scikit-Learn compatible way and model optimization
Home-page: https://github.com/POSidorov/DOPtools
Author: Dr. Pavel Sidorov
Author-email: pavel.o.sidorov@gmail.com
License: LGPLv3
Classifier: Environment :: Plugins
Classifier: Intended Audience :: Science/Research
Classifier: Intended Audience :: Developers
Classifier: Topic :: Scientific/Engineering :: Chemistry
Classifier: Topic :: Software Development :: Libraries :: Python Modules
Classifier: License :: OSI Approved :: GNU Lesser General Public License v3 or later (LGPLv3+)
Classifier: Operating System :: OS Independent
Classifier: Programming Language :: Python
Classifier: Programming Language :: Python :: 3
Classifier: Programming Language :: Python :: 3.9
Classifier: Programming Language :: Python :: 3.10
Classifier: Programming Language :: Python :: 3.11
Requires-Python: >=3.9.0
License-File: LICENSE
